ait/commons/util/__init__.py
ait/commons/util/__main__.py
ait/commons/util/aws_client.py
ait/commons/util/bucket_policy.py
ait/commons/util/cmd.py
ait/commons/util/common.py
ait/commons/util/file_transfer.py
ait/commons/util/local_state.py
ait/commons/util/progress_bar.py
ait/commons/util/upload_service.py
ait/commons/util/user_profile.py
ait/commons/util/command/__init__.py
ait/commons/util/command/area.py
ait/commons/util/command/config.py
ait/commons/util/command/create.py
ait/commons/util/command/delete.py
ait/commons/util/command/download.py
ait/commons/util/command/list.py
ait/commons/util/command/select.py
ait/commons/util/command/sync.py
ait/commons/util/command/upload.py
ait/commons/util/settings/__init__.py
ait/commons/util/settings/covid_util.py
ait/commons/util/settings/hca_util.py
hca_util-0.2.16.dist-info/LICENSE
hca_util-0.2.16.dist-info/METADATA
hca_util-0.2.16.dist-info/WHEEL
hca_util-0.2.16.dist-info/entry_points.txt
hca_util-0.2.16.dist-info/top_level.txt
hca_util-0.2.16.dist-info/RECORD
