Metadata-Version: 2.1
Name: hca-util
Version: 0.2.16
Summary: CLI tool for uploading data to the HCA data platform
Home-page: https://github.com/ebi-ait/hca-util
Author: hca-ingest-dev
Author-email: hca-ingest-dev@ebi.ac.uk
License: Apache License
Platform: MacOS X
Platform: Posix
Classifier: License :: OSI Approved :: Apache Software License
Classifier: Operating System :: MacOS :: MacOS X
Classifier: Operating System :: POSIX
Classifier: Programming Language :: Python :: 3.6
Classifier: Programming Language :: Python :: 3.7
Requires-Python: >=3.6
Requires-Dist: boto3 (==1.12.*)
Requires-Dist: botocore (==1.15.*)
Requires-Dist: filetype (==1.0.7)
Requires-Dist: requests (<3,>=2.20.0)
Requires-Dist: tqdm
